tinycolors/__init__.py
tinycolors/main.py
tinycolors/tprint.py
tinycolors-0.6.7.dist-info/licenses/LICENSE
tinycolors-0.6.7.dist-info/METADATA
tinycolors-0.6.7.dist-info/WHEEL
tinycolors-0.6.7.dist-info/top_level.txt
tinycolors-0.6.7.dist-info/RECORD
