Metadata-Version: 2.4
Name: tinycolors
Version: 0.6.7
Summary: A tiny, useful, and readable color library for fast colors
Author-email: Razka Rizaldi <razka.rizaldis@gmail.com>
License-Expression: MIT
Project-URL: Homepage, https://github.com/tyydev1/tinycolors
Project-URL: Repository, https://github.com/tyydev1/tinycolors
Project-URL: Issues, https://github.com/tyydev1/tinycolors/issues
Keywords: color,ansi,terminal,console,colorize,formatting
Classifier: Development Status :: 4 - Beta
Classifier: Intended Audience :: Developers
Classifier: Programming Language :: Python :: 3
Classifier: Programming Language :: Python :: 3.7
Classifier: Programming Language :: Python :: 3.8
Classifier: Programming Language :: Python :: 3.9
Classifier: Programming Language :: Python :: 3.10
Classifier: Programming Language :: Python :: 3.11
Classifier: Programming Language :: Python :: 3.12
Classifier: Topic :: Software Development :: Libraries :: Python Modules
Classifier: Topic :: Terminals
Requires-Python: >=3.7
License-File: LICENSE
Provides-Extra: dev
Requires-Dist: build>=1.1.1; extra == "dev"
Requires-Dist: furo>=2023.3.27; extra == "dev"
Requires-Dist: pytest>=7.4.4; extra == "dev"
Requires-Dist: sphinx>=5.3.0; extra == "dev"
Requires-Dist: sphinx-autoapi>=2.1.1; extra == "dev"
Dynamic: license-file
